{
    "name": "bs-hapi-mongo-graphql-tests",
    "sources": [{
        "dir": "src",
        "subdirs": true
    }],
    "package-specs": [{
        "module": "commonjs",
        "in-source": true
    }],
    "suffix": ".bs.js",
    "namespace": false,
    "bsc-flags": [
        "-bs-super-errors"
    ],
    "ppx-flags": [
        "./mongoose_ppx/_build/install/default/lib/ppx_bs_mongoose/ppx.exe\\ --as-ppx"
    ],
    "bs-dependencies": [
        "@glennsl/bs-json",
        "reason-future"
    ],
    "refmt": 3
}